sneat/__init__.py
sneat/config.py
sneat/default_config.ini
sneat/evolve.py
sneat/genome.py
sneat/neuralnetwork.py
sneat/normalizer.py
sneat/population.py
sneat/species.py
sneat-1.0.3.dist-info/LICENSE
sneat-1.0.3.dist-info/METADATA
sneat-1.0.3.dist-info/WHEEL
sneat-1.0.3.dist-info/top_level.txt
sneat-1.0.3.dist-info/RECORD
