Metadata-Version: 2.1
Name: sneat
Version: 1.0.3
Summary: Simplified implementation of NEAT (Neuro-Evolution of Augmenting Topologies).
Home-page: https://github.com/bhark/sNEAT
Author: Adrian E. Bratlann
Author-email: aeb@tetrabit.coop
License: GPLv3
Classifier: Development Status :: 3 - Alpha
Classifier: Intended Audience :: Developers
Classifier: Intended Audience :: Education
Classifier: Intended Audience :: Science/Research
Classifier: License :: OSI Approved :: GNU General Public License v3 (GPLv3)
Classifier: Programming Language :: Python :: 3.12
Classifier: Topic :: Scientific/Engineering :: Artificial Intelligence
Classifier: Topic :: Software Development :: Libraries :: Python Modules
License-File: LICENSE
Requires-Dist: matplotlib ==3.9.0
Requires-Dist: networkx ==3.3
Requires-Dist: numpy ==1.26.4
Requires-Dist: tabulate ==0.9.0
Requires-Dist: tqdm ==4.66.4
Provides-Extra: examples
Requires-Dist: gymnasium ==1.0.0a2 ; extra == 'examples'
Requires-Dist: gymnasium[box2d] ; extra == 'examples'
Requires-Dist: gymnasium[classic_control] ; extra == 'examples'
Requires-Dist: gymnasium[mujoco] ; extra == 'examples'
